beam_postgres/__init__.py
beam_postgres/io/__init__.py
beam_postgres/io/postgres.py
beam_postgres/io/retry.py
beam_postgres-0.5.0.dist-info/LICENSE
beam_postgres-0.5.0.dist-info/METADATA
beam_postgres-0.5.0.dist-info/WHEEL
beam_postgres-0.5.0.dist-info/top_level.txt
beam_postgres-0.5.0.dist-info/RECORD
