Metadata-Version: 2.1
Name: beam-postgres
Version: 0.5.0
Summary: Light IO transforms for Postgres read/write in Apache Beam pipelines.
Author: Adam Medziński
License: Apache-2.0
Project-URL: Homepage, https://github.com/medzin/beam-postgres
Keywords: apache beam,beam,postgres,postgresql
Classifier: Development Status :: 3 - Alpha
Classifier: License :: OSI Approved :: Apache Software License
Classifier: Operating System :: POSIX :: Linux
Classifier: Programming Language :: Python
Classifier: Programming Language :: Python :: 3
Classifier: Programming Language :: Python :: 3.8
Classifier: Programming Language :: Python :: 3.9
Classifier: Programming Language :: Python :: 3.10
Classifier: Programming Language :: Python :: 3.11
Classifier: Programming Language :: Python :: 3 :: Only
Classifier: Topic :: Software Development :: Libraries
Classifier: Topic :: Software Development :: Libraries :: Python Modules
Requires-Python: >=3.8
License-File: LICENSE
Requires-Dist: apache-beam <3,>=2.42.0
Requires-Dist: psycopg[binary] <4,>=3.1.4
Provides-Extra: dev
Requires-Dist: bumpver ; extra == 'dev'
Requires-Dist: pip-tools ; extra == 'dev'
Requires-Dist: tox ; extra == 'dev'
Provides-Extra: tests
Requires-Dist: black ; extra == 'tests'
Requires-Dist: flake8 ; extra == 'tests'
Requires-Dist: isort ; extra == 'tests'
Requires-Dist: mypy ; extra == 'tests'
Requires-Dist: pytest >=7 ; extra == 'tests'
